inspect_dense/__init__.py
inspect_dense/getcode.py
inspect_dense-0.2.5.dist-info/LICENSE
inspect_dense-0.2.5.dist-info/METADATA
inspect_dense-0.2.5.dist-info/WHEEL
inspect_dense-0.2.5.dist-info/entry_points.txt
inspect_dense-0.2.5.dist-info/RECORD
