Metadata-Version: 2.1
Name: inspect-dense
Version: 0.2.5
Summary: A tool for recursively describing all files in a directory.
Home-page: https://aimodels.org
License: Apache-2.0
Author: Justin Riddiough
Author-email: justin@visioninit.dev
Requires-Python: >=3.6,<4.0
Classifier: License :: OSI Approved :: Apache Software License
Classifier: License :: OSI Approved :: MIT License
Classifier: Operating System :: OS Independent
Classifier: Programming Language :: Python :: 3
Classifier: Programming Language :: Python :: 3.6
Classifier: Programming Language :: Python :: 3.7
Classifier: Programming Language :: Python :: 3.8
Classifier: Programming Language :: Python :: 3.9
Classifier: Programming Language :: Python :: 3.10
Classifier: Programming Language :: Python :: 3.11
Requires-Dist: gitignore-parser (>=0.1.3,<0.2.0)
Project-URL: Repository, https://github.com/neural-loop/inspect_dense
